igzg/__init__.py
igzg/configManager.py
igzg/mySQL.py
igzg/utils.py
igzg-1.0.0.dist-info/LICENSE
igzg-1.0.0.dist-info/METADATA
igzg-1.0.0.dist-info/WHEEL
igzg-1.0.0.dist-info/top_level.txt
igzg-1.0.0.dist-info/RECORD
