Metadata-Version: 2.1
Name: igzg
Version: 1.0.0
Summary: PYPI tutorial package creation written by suhyeojee
Home-page: https://github.com/suhyeojee/igzg
Author: suhyeojee
Author-email: suhyeojee@gmail.com
Classifier: Programming Language :: Python :: 3
Classifier: License :: OSI Approved :: MIT License
Classifier: Operating System :: Microsoft :: Windows
Requires-Python: >=3.6
License-File: LICENSE
